marshmallow_api_utils/__init__.py
marshmallow_api_utils/fields.py
marshmallow_api_utils/flask_blueprint.py
marshmallow_api_utils/ma_dataclass.py
marshmallow_api_utils/package_finder.py
marshmallow_api_utils/middleware/__init__.py
marshmallow_api_utils/middleware/flask_logging_middleware.py
marshmallow_api_utils/models/__init__.py
marshmallow_api_utils/models/date_time_filter.py
marshmallow_api_utils/models/pageable.py
marshmallow_api_utils/models/sortable.py
marshmallow_api_utils-0.2.5.dist-info/METADATA
marshmallow_api_utils-0.2.5.dist-info/WHEEL
marshmallow_api_utils-0.2.5.dist-info/licenses/LICENSE.md
marshmallow_api_utils-0.2.5.dist-info/RECORD
